flask_pyquery.py
setup.py
Flask_PyQuery.egg-info/PKG-INFO
Flask_PyQuery.egg-info/SOURCES.txt
Flask_PyQuery.egg-info/dependency_links.txt
Flask_PyQuery.egg-info/not-zip-safe
Flask_PyQuery.egg-info/requires.txt
Flask_PyQuery.egg-info/top_level.txt