Metadata-Version: 1.1
Name: Flask-PyQuery
Version: 0.1
Summary: PyQuery templating support for Flask applications.
Home-page: https://github.com/knitori/flask-pyquery
Author: Nitori Kawashiro
Author-email: nitori@chireiden.net
License: BSD
Platform: any
Classifier: Development Status :: 3 - Alpha
Classifier: Environment :: Web Environment
Classifier: Intended Audience :: Developers
Classifier: License :: OSI Approved :: BSD License
Classifier: Operating System :: OS Independent
Classifier: Programming Language :: Python :: 3
Classifier: Topic :: Internet :: WWW/HTTP :: Dynamic Content
Classifier: Topic :: Software Development :: Libraries :: Python Modules
